CHANGES.txt
MANIFEST.in
README.txt
development.ini
production.ini
pytest.ini
setup.py
wheat_sample_app/__init__.py
wheat_sample_app/routes.py
wheat_sample_app/tests.py
wheat_sample_app.egg-info/PKG-INFO
wheat_sample_app.egg-info/SOURCES.txt
wheat_sample_app.egg-info/dependency_links.txt
wheat_sample_app.egg-info/entry_points.txt
wheat_sample_app.egg-info/not-zip-safe
wheat_sample_app.egg-info/requires.txt
wheat_sample_app.egg-info/top_level.txt
wheat_sample_app/models/__init__.py
wheat_sample_app/models/meta.py
wheat_sample_app/models/mymodel.py
wheat_sample_app/scripts/__init__.py
wheat_sample_app/scripts/initializedb.py
wheat_sample_app/static/pyramid-16x16.png
wheat_sample_app/static/pyramid.png
wheat_sample_app/static/theme.css
wheat_sample_app/templates/404.jinja2
wheat_sample_app/templates/layout.jinja2
wheat_sample_app/templates/mytemplate.jinja2
wheat_sample_app/views/__init__.py
wheat_sample_app/views/default.py
wheat_sample_app/views/notfound.py